Workbook

Sheet Assumptions
A1: Municipal Bill Auditor: pricing model assumptions
A2: How to use: change only the blue numbers on yellow cells. Everything on the Model tab recalculates. Every starting value is an illustrative guess, not researched data; replace them as you learn from real customers.
A4: Assumption | B4: Year 1 | C4: Year 2 | D4: Year 3 | E4: Unit | F4: Why this starting value
A5: 1. Success fees: businesses and body corporates
A6: New clients signed in the year | B6: 10 | C6: 30 | D6: 60 | E6: clients | F6: Guess: a founder-led sales pace, growing as case studies build up.
A7: Average municipal bill per client | B7: 150000 | C7: 150000 | D7: 150000 | E7: R / month | F7: Illustrative mid-sized complex or business. Check against the first 10 prospects.
A8: Clients where a recoverable error is found | B8: 0.4 | C8: 0.4 | D8: 0.4 | E8: % of clients | F8: Guess. This is the number most worth testing early with real bills.
A9: Back-refund won, as % of one year's bill | B9: 0.05 | C9: 0.05 | D9: 0.05 | E9: % of annual bill | F9: Guess based on typical estimated-reading and tariff errors.
A10: Clients with an ongoing fix (e.g. wrong tariff) | B10: 0.2 | C10: 0.2 | D10: 0.2 | E10: % of clients | F10: Share of clients where the error would have kept repeating, like the Tshwane tariff case.
A11: Future saving from the ongoing fix | B11: 0.05 | C11: 0.05 | D11: 0.05 | E11: % of annual bill | F11: Guess: the monthly overcharge that stops after the fix.
A12: Success fee | B12: 0.25 | C12: 0.25 | D12: 0.25 | E12: % of amount won | F12: Typical contingency range for utility-audit work is about 20% to 35%.
A13: Share of fees collected in the same year | B13: 0.6 | C13: 0.6 | D13: 0.6 | E13: % of fees | F13: Refunds land as account credits after months; the rest is collected next year.
A14: Staff cost to run one business dispute | B14: 3000 | C14: 3000 | D14: 3000 | E14: R / dispute | F14: Guess: about a day of an analyst's time plus municipal follow-up.
A15: 2. Subscriptions: landlords and managing agents
A16: Units under subscription at year end | B16: 500 | C16: 2500 | D16: 7500 | E16: units | F16: Guess: 2 agents in Year 1, about 10 in Year 2, about 25 in Year 3, at around 250 to 300 units each.
A17: Subscription price per unit | B17: 50 | C17: 50 | D17: 55 | E17: R / unit / month | F17: Middle of the R30 to R80 range suggested earlier.
A18: Disputes raised per unit per year | B18: 0.1 | C18: 0.1 | D18: 0.1 | E18: disputes / unit | F18: Guess: one in ten units needs a dispute each year.
A19: Staff cost per subscriber dispute | B19: 400 | C19: 350 | D19: 300 | E19: R / dispute | F19: Smaller residential disputes, cheaper as templates and automation improve.
A20: 3. Free tier: households
A21: Active free households (average in the year) | B21: 2000 | C21: 10000 | D21: 30000 | E21: households | F21: Guess. Organic growth through ratepayer groups and social media.
A22: Households that pay for a managed dispute | B22: 0.03 | C22: 0.03 | D22: 0.03 | E22: % per year | F22: Guess: a small share hit by a large wrong bill.
A23: Managed dispute fee for a household | B23: 299 | C23: 299 | D23: 349 | E23: R / dispute | F23: Within the R199 to R499 range suggested earlier.
A24: Staff cost per household dispute | B24: 150 | C24: 120 | D24: 100 | E24: R / dispute | F24: Mostly automated letter and tracking, with light human review.
A25: 4. Running costs
A26: Cost to read and check one bill (OCR, AI, storage) | B26: 4 | C26: 3 | D26: 2.5 | E26: R / bill | F26: Guess. Measure this on your first prototype.
A27: Bills per account per year | B27: 12 | C27: 12 | D27: 12 | E27: bills | F27: Monthly municipal bills.
A28: Fixed team and overhead | B28: 900000 | C28: 2400000 | D28: 4800000 | E28: R / year | F28: Guess: founders plus a part-time developer, then a small team. Includes POPIA compliance, legal, and hosting.
A29: POPIA, security and legal (inside fixed above) | B29: 120000 | C29: 200000 | D29: 300000 | E29: R / year | F29: Shown for visibility only; already counted in the fixed cost line. Information officer, audits, legal templates.

Sheet Model
A1: Municipal Bill Auditor: revenue and profit by year
A2: All figures in rand. Everything here is calculated from the Assumptions tab; don't type over it.
A4: Rand | B4: Year 1 | C4: Year 2 | D4: Year 3
A5: Success fees: businesses and body corporates
A6: Clients signed | B6: =Assumptions!B$6 -> 10 | C6: =Assumptions!C$6 -> 30 | D6: =Assumptions!D$6 -> 60
A7: Clients with an error found | B7: =B6*Assumptions!B$8 -> 4 | C7: =C6*Assumptions!C$8 -> 12 | D7: =D6*Assumptions!D$8 -> 24
A8: Back-refunds won for clients | B8: =B7*Assumptions!B$7*12*Assumptions!B$9 -> 360000 | C8: =C7*Assumptions!C$7*12*Assumptions!C$9 -> 1080000 | D8: =D7*Assumptions!D$7*12*Assumptions!D$9 -> 2160000
A9: Future savings won (first 12 months) | B9: =B6*Assumptions!B$10*Assumptions!B$7*12*Assumptions!B$11 -> 180000 | C9: =C6*Assumptions!C$10*Assumptions!C$7*12*Assumptions!C$11 -> 540000 | D9: =D6*Assumptions!D$10*Assumptions!D$7*12*Assumptions!D$11 -> 1080000
A10: Success fees earned | B10: =(B8+B9)*Assumptions!B$12 -> 135000 | C10: =(C8+C9)*Assumptions!C$12 -> 405000 | D10: =(D8+D9)*Assumptions!D$12 -> 810000
A11: Success fees collected (cash) | B11: =B10*Assumptions!B$13 -> 81000 | C11: =C10*Assumptions!C$13+B10*(1-Assumptions!B$13) -> 297000 | D11: =D10*Assumptions!D$13+C10*(1-Assumptions!C$13) -> 648000
A12: Subscriptions: landlords and managing agents
A13: Average units subscribed in the year | B13: =Assumptions!B$16/2 -> 250 | C13: =(Assumptions!B$16+Assumptions!C$16)/2 -> 1500 | D13: =(Assumptions!C$16+Assumptions!D$16)/2 -> 5000
A14: Subscription revenue | B14: =B13*Assumptions!B$17*12 -> 150000 | C14: =C13*Assumptions!C$17*12 -> 900000 | D14: =D13*Assumptions!D$17*12 -> 3300000
A15: Free tier: households
A16: Paid household disputes | B16: =Assumptions!B$21*Assumptions!B$22 -> 60 | C16: =Assumptions!C$21*Assumptions!C$22 -> 300 | D16: =Assumptions!D$21*Assumptions!D$22 -> 900
A17: Household dispute revenue | B17: =B16*Assumptions!B$23 -> 17940 | C17: =C16*Assumptions!C$23 -> 89700 | D17: =D16*Assumptions!D$23 -> 314100
A18: Totals
A19: Total revenue (cash) | B19: =B11+B14+B17 -> 248940 | C19: =C11+C14+C17 -> 1286700 | D19: =D11+D14+D17 -> 4262100
A20: Bills processed | B20: =(B6+B13+Assumptions!B$21)*Assumptions!B$27 -> 27120 | C20: =(C6+C13+Assumptions!C$21)*Assumptions!C$27 -> 138360 | D20: =(D6+D13+Assumptions!D$21)*Assumptions!D$27 -> 420720
A21: Cost of reading bills | B21: =B20*Assumptions!B$26 -> 108480 | C21: =C20*Assumptions!C$26 -> 415080 | D21: =D20*Assumptions!D$26 -> 1051800
A22: Cost of running disputes | B22: =B7*Assumptions!B$14+B13*Assumptions!B$18*Assumptions!B$19+B16*Assumptions!B$24 -> 31000 | C22: =C7*Assumptions!C$14+C13*Assumptions!C$18*Assumptions!C$19+C16*Assumptions!C$24 -> 124500 | D22: =D7*Assumptions!D$14+D13*Assumptions!D$18*Assumptions!D$19+D16*Assumptions!D$24 -> 312000
A23: Gross profit | B23: =B19-B21-B22 -> 109460 | C23: =C19-C21-C22 -> 747120 | D23: =D19-D21-D22 -> 2898300
A24: Gross margin | B24: =IF(B19=0,0,B23/B19) -> 0.43970435 | C24: =IF(C19=0,0,C23/C19) -> 0.58064817 | D24: =IF(D19=0,0,D23/D19) -> 0.68001689
A25: Fixed team and overhead | B25: =Assumptions!B$28 -> 900000 | C25: =Assumptions!C$28 -> 2400000 | D25: =Assumptions!D$28 -> 4800000
A26: Operating profit | B26: =B23-B25 -> -790540 | C26: =C23-C25 -> -1652880 | D26: =D23-D25 -> -1901700
A27: Cumulative profit (cash needed if negative) | B27: =B26 -> -790540 | C27: =B27+C26 -> -2443420 | D27: =C27+D26 -> -4345120
A28: Revenue mix
A29: Success fees | B29: =IF(B19=0,0,B11/B19) -> 0.32537961 | C29: =IF(C19=0,0,C11/C19) -> 0.23082304 | D29: =IF(D19=0,0,D11/D19) -> 0.15203773
A30: Subscriptions | B30: =IF(B19=0,0,B14/B19) -> 0.60255483 | C30: =IF(C19=0,0,C14/C19) -> 0.69946374 | D30: =IF(D19=0,0,D14/D19) -> 0.77426621
A31: Households | B31: =IF(B19=0,0,B17/B19) -> 0.072065558 | C31: =IF(C19=0,0,C17/C19) -> 0.06971322 | D31: =IF(D19=0,0,D17/D19) -> 0.073696065
A33: One example business client
A34: Back-refund if an error is found | B34: =Assumptions!B$7*12*Assumptions!B$9 -> 90000 | C34: =Assumptions!C$7*12*Assumptions!C$9 -> 90000 | D34: =Assumptions!D$7*12*Assumptions!D$9 -> 90000
A35: Your success fee on that refund | B35: =B34*Assumptions!B$12 -> 22500 | C35: =C34*Assumptions!C$12 -> 22500 | D35: =D34*Assumptions!D$12 -> 22500
